mcp_demo/__init__.py
mcp_demo/__main__.py
mcp_demo/server.py
mcp_demo/views/__init__.py
mcp_demo/views/input_dialogue.py
hw_mcp_demo-0.1.4.dist-info/METADATA
hw_mcp_demo-0.1.4.dist-info/WHEEL
hw_mcp_demo-0.1.4.dist-info/entry_points.txt
hw_mcp_demo-0.1.4.dist-info/RECORD
