Metadata-Version: 2.4
Name: hw-mcp-demo
Version: 0.1.4
Summary: Huawei MCP Plugin - Human in the Loop
Requires-Python: >=3.10
Requires-Dist: hatchling>=1.27.0
Requires-Dist: mcp[cli]>=1.13.1
